advancedbilling/__init__.py
advancedbilling/advanced_billing_client.py
advancedbilling/api_helper.py
advancedbilling/configuration.py
advancedbilling/controllers/__init__.py
advancedbilling/controllers/advance_invoice_controller.py
advancedbilling/controllers/api_exports_controller.py
advancedbilling/controllers/base_controller.py
advancedbilling/controllers/billing_portal_controller.py
advancedbilling/controllers/components_controller.py
advancedbilling/controllers/coupons_controller.py
advancedbilling/controllers/custom_fields_controller.py
advancedbilling/controllers/customers_controller.py
advancedbilling/controllers/events_based_billing_segments_controller.py
advancedbilling/controllers/events_controller.py
advancedbilling/controllers/insights_controller.py
advancedbilling/controllers/invoices_controller.py
advancedbilling/controllers/offers_controller.py
advancedbilling/controllers/payment_profiles_controller.py
advancedbilling/controllers/product_families_controller.py
advancedbilling/controllers/product_price_points_controller.py
advancedbilling/controllers/products_controller.py
advancedbilling/controllers/proforma_invoices_controller.py
advancedbilling/controllers/reason_codes_controller.py
advancedbilling/controllers/referral_codes_controller.py
advancedbilling/controllers/sales_commissions_controller.py
advancedbilling/controllers/sites_controller.py
advancedbilling/controllers/subscription_components_controller.py
advancedbilling/controllers/subscription_group_invoice_account_controller.py
advancedbilling/controllers/subscription_group_status_controller.py
advancedbilling/controllers/subscription_groups_controller.py
advancedbilling/controllers/subscription_invoice_account_controller.py
advancedbilling/controllers/subscription_notes_controller.py
advancedbilling/controllers/subscription_products_controller.py
advancedbilling/controllers/subscription_status_controller.py
advancedbilling/controllers/subscriptions_controller.py
subtain_apimatic_sdk-4.0.0.dist-info/LICENSE
subtain_apimatic_sdk-4.0.0.dist-info/METADATA
subtain_apimatic_sdk-4.0.0.dist-info/WHEEL
subtain_apimatic_sdk-4.0.0.dist-info/top_level.txt
subtain_apimatic_sdk-4.0.0.dist-info/RECORD
