Metadata-Version: 2.1
Name: subtain-apimatic-sdk
Version: 4.0.0
Summary: This is a test package publishing, Please ignore
Author-email: Subtain <Syed.subtain@apimatic.io>
Project-URL: Documentation, https://apimatic.io
Keywords: apimatic ,Test
Requires-Python: >=3.7
License-File: LICENSE
Requires-Dist: apimatic-core ~=0.2.0
Requires-Dist: apimatic-core-interfaces ~=0.1.0
Requires-Dist: apimatic-requests-client-adapter ~=0.1.0
Requires-Dist: python-dateutil ~=2.8.1
Requires-Dist: enum34 >=1.1.10,~=1.1
Requires-Dist: deprecation ~=2.1
Requires-Dist: jsonschema ~=3.2.0
Provides-Extra: testutils
Requires-Dist: pytest >=7.2.2 ; extra == 'testutils'
